[
  {
    "id": 1,
    "title": "아시아나항공 홈페이지 고도화",
    "period": "2015.01 ~ 2015.03",
    "summary": "아시아나 항공 홈페이지 기능 개선",
    "details": [
      "여행 동반자 추가 할인 코드 관리 관리자 화면 개발"
    ],
    "goals": [],
    "techStack": [
      {
        "name": "Java",
        "layer": "Language"
      },
      {
        "name": "JavaScript (jQuery)",
        "layer": "Frontend"
      },
      {
        "name": "JSP",
        "layer": "View Template"
      },
      {
        "name": "Oracle",
        "layer": "Database"
      },
      {
        "name": "Spring",
        "layer": "Framework"
      },
      {
        "name": "MyBatis",
        "layer": "ORM"
      }
    ],
    "troubleshooting": [],
    "infra": [],
    "achievements": [
      "처음 맡은 개발 업무로 Spring을 사용한 웹 애플리케이션 개발과 항공업무에 대한 전반적인 이해를 갖춤"
    ],
    "links": []
  },
  {
    "id": 2,
    "title": "제주항공 기업우대 서비스 구축",
    "period": "2015.04 ~ 2015.06",
    "summary": "제주항공 홈페이지 기업회원 우대 기능 및 관리 기능 구축",
    "details": [
      "기업 회원 가입 프론트엔드 개발 (pc, 모바일 웹, 모바일 앱)"
    ],
    "goals": [],
    "techStack": [
      {
        "name": "Java",
        "layer": "Language"
      },
      {
        "name": "JavaScript (jQuery)",
        "layer": "Frontend"
      },
      {
        "name": "JSP",
        "layer": "View Template"
      },
      {
        "name": "DB2",
        "layer": "Database"
      },
      {
        "name": "Spring",
        "layer": "Framework"
      },
      {
        "name": "MyBatis",
        "layer": "ORM"
      }
    ],
    "troubleshooting": [],
    "infra": [],
    "achievements": [
      "모바일 앱 플랫폼 경험"
    ],
    "links": []
  },
  {
    "id": 3,
    "title": "BSP/CASS 선도개발",
    "period": "2015.06 ~ 2016.01",
    "summary": "은행 합병으로 인한 BSP 정산 업무 통합 환경 구축",
    "details": [
      "C언어 기반 pro*c언어로 작성된 소스 코드와 호출하는 sp(stored procedure) 분석, 수정 및 디버깅"
    ],
    "goals": [],
    "techStack": [
      {
        "name": "Pro*C",
        "layer": "Language"
      },
      {
        "name": "Oracle",
        "layer": "Database"
      }
    ],
    "troubleshooting": [],
    "infra": [],
    "achievements": [
      "Pro*C 기반 프로그램 및 프로시저 개발 경험",
      "Stored Procedure 분석·수정·개발 경험을 바탕으로 SQLD 자격 취득"
    ],
    "links": []
  },
  {
    "id": 4,
    "title": "제주항공 사전수하물 구매 기능 추가",
    "period": "2016.02 ~ 2016.04",
    "summary": "사전 수하물 온라인 판매 시스템 구축",
    "details": [
      "모바일 웹, 모바일 앱 프론트엔드 개발",
      "보안성 검토 솔루션인 Code-Ray 사용하여 취약점 개선"
    ],
    "goals": [],
    "techStack": [
      {
        "name": "Java",
        "layer": "Language"
      },
      {
        "name": "JavaScript (jQuery)",
        "layer": "Frontend"
      },
      {
        "name": "JSP",
        "layer": "View Template"
      },
      {
        "name": "DB2",
        "layer": "Database"
      },
      {
        "name": "Spring",
        "layer": "Framework"
      },
      {
        "name": "MyBatis",
        "layer": "ORM"
      }
    ],
    "troubleshooting": [],
    "infra": [
      {
        "name": "jeus",
        "layer": "Application Server"
      }
    ],
    "achievements": [
      "검출된 SQL Injection, XSS 등 보안 취약점 해결",
      "Critical/High 레벨 이슈를 모두 해소"
    ],
    "links": []
  },
  {
    "id": 5,
    "title": "에어서울 수입관리 시스템 개발",
    "period": "2016.04 ~ 2016.11",
    "summary": "자사 수입관리 솔루션 고객사 요구에 맞춰 개선하여 구축",
    "details": [
      "프로젝트 초기 개발 환경 구성",
      "사용자 매뉴얼 작성",
      "sp(Stored Procedure) 수정 및 작성"
    ],
    "goals": [],
    "techStack": [
      {
        "name": "C#",
        "layer": "Language"
      },
      {
        "name": "ASPX",
        "layer": "View Template"
      },
      {
        "name": "MSSQL",
        "layer": "Database"
      },
      {
        "name": "ASP.NET",
        "layer": "Framework"
      }
    ],
    "troubleshooting": [],
    "infra": [],
    "achievements": [
      "초기 전체 개발 환경 구성",
      "프로젝트 기간 내 고객사 요구사항을 반영한 수입관리 솔루션 전달 완료"
    ],
    "links": []
  },
  {
    "id": 6,
    "title": "제주항공 ABB 정산 시스템 구축",
    "period": "2016.12 ~ 2017.04",
    "summary": "제주항공 수입관리 ABB 정산 시스템 웹 애플리케이션 개발",
    "details": [
      "ABB 정산 시스템 레포트·대사 기능(집계/상세) 개발"
    ],
    "goals": [],
    "techStack": [
      {
        "name": "Java",
        "layer": "Language"
      },
      {
        "name": "JavaScript (jQuery, jqGrid)",
        "layer": "Frontend"
      },
      {
        "name": "JSP",
        "layer": "View Template"
      },
      {
        "name": "Oracle",
        "layer": "Database"
      },
      {
        "name": "Spring",
        "layer": "Framework"
      },
      {
        "name": "MyBatis",
        "layer": "ORM"
      }
    ],
    "troubleshooting": [],
    "infra": [
      {
        "name": "jeus",
        "layer": "Application Server"
      }
    ],
    "achievements": [],
    "links": []
  },
  {
    "id": 7,
    "title": "제주항공 홈페이지 러시아어 추가",
    "period": "2017.07 ~ 2017.10",
    "summary": "제주항공 홈페이지 다국어 (러시아어) 추가",
    "details": [
      "홈페이지 내 한글 문구 정리하여 번역 요청",
      "러시아어 번역 문구 json 형식으로 작성 및 적용"
    ],
    "goals": [],
    "techStack": [
      {
        "name": "Java",
        "layer": "Language"
      },
      {
        "name": "JavaScript (jQuery)",
        "layer": "Frontend"
      },
      {
        "name": "JSP",
        "layer": "View Template"
      },
      {
        "name": "Spring",
        "layer": "Framework"
      }
    ],
    "troubleshooting": [
      {
        "title": "번역 오류로 인한 전면 재작업",
        "problem": "프로젝트 후반 번역 품질이 낮은것 인지, 사이트 전체 재반영 필요",
        "solution": "사전 제작한 '번역→JSON' 변환 유틸로 전체 페이지 번역 데이터를 수분 내 재생성·반영해 일정 지연 없이 완료"
      }
    ],
    "infra": [],
    "achievements": [
      "프로젝트 후반 번역 오류로 전면 재작업이 필요한 상황에서도 일정 지연 없이 기간 내 완료",
      "json locale 기반 다국어 리소스 변환·적용 프로세스를 통해 다국어 처리 경험",
      "사전 제작한 자동화 유틸로 반복 반영 작업을 수분 단위로 단축, 재작업 리스크 최소화"
    ],
    "links": []
  },
  {
    "id": 8,
    "title": "제주항공 홈페이지 최저가 운임 적용",
    "period": "2017.09 ~ 2017.12",
    "summary": "모바일 판매 채널에 최저가 운임 조회 기능 적용",
    "details": [
      "모바일 웹 최저가 검색 화면 개발",
      "여행 테마별, 월별, 일별 최저 운임 데이터 조회 기능 개발"
    ],
    "goals": [],
    "techStack": [
      {
        "name": "Java",
        "layer": "Language"
      },
      {
        "name": "JavaScript (jQuery)",
        "layer": "Frontend"
      },
      {
        "name": "JSP",
        "layer": "View Template"
      },
      {
        "name": "DB2",
        "layer": "Database"
      },
      {
        "name": "Spring",
        "layer": "Framework"
      },
      {
        "name": "MyBatis",
        "layer": "ORM"
      }
    ],
    "troubleshooting": [],
    "infra": [
      {
        "name": "jeus",
        "layer": "Application Server"
      }
    ],
    "achievements": [],
    "links": []
  },
  {
    "id": 9,
    "title": "제주항공 홈페이지 국내선 Fare family",
    "period": "2017.12 ~ 2018.05",
    "summary": "국내선 항공권 특가, 할인, 일반 운임 체계를 Fly, Flybag, Flybag+ 운임 체계로 전환",
    "details": [
      "프론트엔드 화면 개발",
      "항공권 구매 및 변경 시 구매 가능한 항공권 조회 화면 개발"
    ],
    "goals": [],
    "techStack": [
      {
        "name": "Java",
        "layer": "Language"
      },
      {
        "name": "JavaScript (jQuery)",
        "layer": "Frontend"
      },
      {
        "name": "JSP",
        "layer": "View Template"
      },
      {
        "name": "Oracle",
        "layer": "Database"
      },
      {
        "name": "Spring",
        "layer": "Framework"
      },
      {
        "name": "MyBatis",
        "layer": "ORM"
      }
    ],
    "troubleshooting": [],
    "infra": [
      {
        "name": "jeus",
        "layer": "Application Server"
      }
    ],
    "achievements": [],
    "links": []
  },
  {
    "id": 10,
    "title": "제주항공 통합정산 애플리케이션 개선",
    "period": "2018.07 ~ 2019.01",
    "summary": "제주항공 업무 프로그램 중 하나인 통합정산 사이트 개선",
    "details": [
      "매출 집계 및 에러매출 현황 등 오류 개선",
      "gpg 방식으로 암호화된 판매 데이터 파일 ftp 접속 다운로드 및 데이터베이스 저장 배치 프로그램 개발",
      "신규 레포트 화면 개발"
    ],
    "goals": [],
    "techStack": [
      {
        "name": "Java",
        "layer": "Language"
      },
      {
        "name": "JavaScript (jQuery)",
        "layer": "Frontend"
      },
      {
        "name": "JSP",
        "layer": "View Template"
      },
      {
        "name": "Oracle",
        "layer": "Database"
      },
      {
        "name": "Spring",
        "layer": "Framework"
      },
      {
        "name": "MyBatis",
        "layer": "ORM"
      }
    ],
    "troubleshooting": [],
    "infra": [],
    "achievements": [
      "저장 데이터 증가로 느려진 조회 쿼리, 인덱스 최적화와 조인 순서 개선으로 체감 성능 70~85% 단축"
    ],
    "links": []
  },
  {
    "id": 11,
    "title": "제주항공 홈페이지 국제선 Fare family",
    "period": "2019.02 ~ 2019.06",
    "summary": "국제선 항공권 특가, 할인, 일반 운임 체계를 Fly, Flybag, Flybag+ 운임 체계로 전환",
    "details": [
      "항공권 구매 및 변경 시 구매 가능한 항공권 조회 화면 개발",
      "신입 직원 멘토링"
    ],
    "goals": [],
    "techStack": [
      {
        "name": "Java",
        "layer": "Language"
      },
      {
        "name": "JavaScript (jQuery)",
        "layer": "Frontend"
      },
      {
        "name": "JSP",
        "layer": "View Template"
      },
      {
        "name": "Oracle",
        "layer": "Database"
      },
      {
        "name": "Spring",
        "layer": "Framework"
      },
      {
        "name": "MyBatis",
        "layer": "ORM"
      }
    ],
    "troubleshooting": [],
    "infra": [
      {
        "name": "jeus",
        "layer": "Application Server"
      }
    ],
    "achievements": [],
    "links": []
  },
  {
    "id": 12,
    "title": "제주항공 홈페이지 뉴클래스 적용",
    "period": "2019.06 ~ 2019.09",
    "summary": "제주항공 항공권 운임 체계 Fly, Flybag, Flybag+ 에 새로운 뉴클래스 운임 개념 추가",
    "details": [
      "항공권 구매 및 변경 시 구매 가능한 항공권 조회 화면 고도화"
    ],
    "goals": [],
    "techStack": [
      {
        "name": "Java",
        "layer": "Language"
      },
      {
        "name": "JavaScript (jQuery)",
        "layer": "Frontend"
      },
      {
        "name": "JSP",
        "layer": "View Template"
      },
      {
        "name": "Oracle",
        "layer": "Database"
      },
      {
        "name": "Spring",
        "layer": "Framework"
      },
      {
        "name": "MyBatis",
        "layer": "ORM"
      }
    ],
    "troubleshooting": [],
    "infra": [],
    "achievements": [],
    "links": []
  },
  {
    "id": 13,
    "title": "수입관리 솔루션 마이그레이션",
    "period": "2019.12 ~ 2020.03",
    "summary": "ASP.NET 기반 수입관리 솔루션 Spring Framework 기반으로 개발",
    "details": [
      "Project Leader 역할을 수행하며, 애플리케이션 개발 환경 구성 및 주요 공통 기능 개발",
      "배치 프로그램 실행 환경 구성",
      "C# 언어로 작성된 코드 java 언어로 변환하는 가이드 작성 및 배포"
    ],
    "goals": [],
    "techStack": [
      {
        "name": "Java",
        "layer": "Language"
      },
      {
        "name": "JavaScript (jQuery, jqGrid)",
        "layer": "Frontend"
      },
      {
        "name": "JSP",
        "layer": "View Template"
      },
      {
        "name": "MSSQL",
        "layer": "Database"
      },
      {
        "name": "Spring",
        "layer": "Framework"
      },
      {
        "name": "Bootstrap",
        "layer": "CSS Framework"
      },
      {
        "name": "MyBatis",
        "layer": "ORM"
      }
    ],
    "troubleshooting": [],
    "infra": [],
    "achievements": [
      "애플리케이션 수준 마이그레이션 경험",
      "웹 애플리케이션 개발 환경 전체 구성 경험"
    ],
    "links": []
  },
  {
    "id": 14,
    "title": "업무용 애플리케이션 고도화",
    "period": "2020.03 ~ 2020.07",
    "summary": "아시아나항공 여행사 전용 내부 웹 애플리케이션 로그 기록 기능 개선 및 보안 강화",
    "details": [
      "로그인 보안 관련 기능 추가 (일정 주기마다 비밀번호 강제 변경, 특정 횟수 이상 암호 불일치할 경우 계정 잠금, 최근 사용한 암호 재사용 불가)",
      "사용자 그룹별 브라우저 이벤트 내역 데이터베이스 적재 기능 추가"
    ],
    "goals": [],
    "techStack": [
      {
        "name": "Java",
        "layer": "Language"
      },
      {
        "name": "JavaScript (jQuery)",
        "layer": "Frontend"
      },
      {
        "name": "MSSQL",
        "layer": "Database"
      },
      {
        "name": "Spring",
        "layer": "Framework"
      },
      {
        "name": "webSquare",
        "layer": "Framework"
      },
      {
        "name": "MyBatis",
        "layer": "ORM"
      }
    ],
    "troubleshooting": [],
    "infra": [],
    "achievements": [
      "개발 PM 으로 투입되어 일정 관리 및 기능 전체 개발 주도",
      "애노테이션과 리플렉션 활용, 중복 코드 제거로 유지 보수성 증대"
    ],
    "links": []
  },
  {
    "id": 15,
    "title": "통합 회원 관리",
    "period": "2021.09 ~ 2021.11",
    "summary": "통합 회원 인증 프로세스 개발",
    "details": [
      "마이크로 서비스 간 통합 인증 환경 제공",
      "통합 회원 정보 관리 서비스 개발"
    ],
    "goals": [],
    "techStack": [
      {
        "name": "Java",
        "layer": "Language"
      },
      {
        "name": "Spring Boot",
        "layer": "Framework"
      },
      {
        "name": "Spring Data JPA",
        "layer": "ORM"
      },
      {
        "name": "MSSQL",
        "layer": "Database"
      },
      {
        "name": "redis",
        "layer": "Database"
      }
    ],
    "troubleshooting": [],
    "infra": [
      {
        "name": "azure",
        "layer": "Cloud"
      },
      {
        "name": "Azure kubernetes Service",
        "layer": "Container Orchestration"
      }
    ],
    "achievements": [
      "마이크로서비스 간 공통으로 사용할 수 있는 통합 로그인 처리 흐름을 설계·구현해 인증 체계 일원화",
      "서비스 간 통합 로그인 환경을 제공하여 사용자 인증 경험과 운영 효율 개선",
      "통합 회원 정보 조회 서비스를 개발해 분산된 회원 데이터를 일관되게 조회·활용할 수 있는 기반 마련"
    ],
    "links": []
  },
  {
    "id": 16,
    "title": "수출입 물류 지원 솔루션 ZimGo 서비스 개발",
    "period": "2021.11 ~ 2023.08",
    "summary": "ZimGo 서비스 백엔드 서버 개발",
    "details": [
      "백엔드 서버 개발 리드",
      "기능 전방에 대한 설계 및 구현"
    ],
    "goals": [],
    "techStack": [
      {
        "name": "Java",
        "layer": "Language"
      },
      {
        "name": "Spring Boot",
        "layer": "Framework"
      },
      {
        "name": "Spring Data JPA",
        "layer": "ORM"
      },
      {
        "name": "MSSQL",
        "layer": "Database"
      },
      {
        "name": "redis",
        "layer": "Database"
      }
    ],
    "troubleshooting": [],
    "infra": [
      {
        "name": "azure",
        "layer": "Cloud"
      },
      {
        "name": "Azure kubernetes Service",
        "layer": "Container Orchestration"
      }
    ],
    "achievements": [
      "신규 수출입 물류 SaaS의 개발 초기 단계부터 운영 환경 런칭까지 전 과정(설계-개발-배포-운영)을 경험",
      "서버 간 통신 구조와 도메인별 데이터베이스 설계로 기능 확장",
      "백엔드 개발 리드로서 코드 리뷰와 구현 방향 정렬을 통해 팀 개발 품질 향상에 기여"
    ],
    "links": []
  },
  {
    "id": 17,
    "title": "OV (Ocean Visibility) 트래킹 구조 통합 및 CQRS 적용",
    "period": "2025.01 ~ ",
    "summary": "B/L, Container, Booking 트래킹 구조를 통합하고 조회·등록 성능을 개선한 OV 서비스 최적화 프로젝트",
    "details": [
      "B/L, Container, Booking 트래킹 데이터 구조를 단일 모델로 통합",
      "트래킹 ID 기반 통합 조회 구조를 설계해 단일 화면/API에서 일괄 조회 가능한 기반 마련",
      "B/L 등록 차감 로직 개선으로 대량 등록 처리 시간 단축 및 동일 건수 기준 처리 시간 일관성 확보"
    ],
    "goals": [],
    "techStack": [
      {
        "name": "Java",
        "layer": "Language"
      },
      {
        "name": "Kotlin",
        "layer": "Language"
      },
      {
        "name": "Spring Boot",
        "layer": "Framework"
      },
      {
        "name": "Spring Data JPA",
        "layer": "ORM"
      },
      {
        "name": "MSSQL",
        "layer": "Database"
      },
      {
        "name": "Azure Cosmos DB",
        "layer": "Database"
      },
      {
        "name": "redis",
        "layer": "Database"
      }
    ],
    "troubleshooting": [],
    "infra": [
      {
        "name": "azure",
        "layer": "Cloud"
      },
      {
        "name": "Azure kubernetes Service",
        "layer": "Container Orchestration"
      }
    ],
    "achievements": [],
    "links": []
  }
]
